dash_template_rendering/__init__.py
dash_template_rendering/template_renderer.py
dash_template_rendering/templating.py
dash_template_rendering-0.0.1b5.dist-info/LICENSE
dash_template_rendering-0.0.1b5.dist-info/METADATA
dash_template_rendering-0.0.1b5.dist-info/WHEEL
dash_template_rendering-0.0.1b5.dist-info/top_level.txt
dash_template_rendering-0.0.1b5.dist-info/RECORD
