Metadata-Version: 2.1
Name: dash-template-rendering
Version: 0.0.1b5
Summary: Dash Python extention for rendering Jinja2 templates.
Author-email: Patrick Schleiter <git.pschleiter@gmail.com>
Project-URL: Source Code, https://github.com/pschleiter/dash-template-rendering
Classifier: Development Status :: 4 - Beta
Classifier: Environment :: Web Environment
Classifier: Intended Audience :: Developers
Classifier: License :: OSI Approved :: MIT License
Classifier: Operating System :: OS Independent
Classifier: Programming Language :: Python
Classifier: Programming Language :: Python :: 3
Classifier: Programming Language :: Python :: 3.8
Classifier: Programming Language :: Python :: 3.9
Classifier: Programming Language :: Python :: 3.10
Classifier: Framework :: Dash
Classifier: Topic :: Internet :: WWW/HTTP :: Dynamic Content
Classifier: Topic :: Software Development :: Libraries :: Python Modules
Requires-Python: >=3.8
License-File: LICENSE
Requires-Dist: dash
Requires-Dist: plotly
Requires-Dist: flask
Requires-Dist: markupsafe
Requires-Dist: Jinja2
Requires-Dist: beautifulsoup4
